ros2setup/__init__.py
ros2setup/ros2setup.py
ros2setup-1.1.dist-info/LICENSE
ros2setup-1.1.dist-info/METADATA
ros2setup-1.1.dist-info/WHEEL
ros2setup-1.1.dist-info/top_level.txt
ros2setup-1.1.dist-info/RECORD
