Metadata-Version: 2.1
Name: ros2setup
Version: 1.1
Summary: Python library for the ROS2 module setup
Home-page: https://github.com/Frederic98/ros2_setup
Author: Frederic
License: UNKNOWN
Platform: UNKNOWN
Classifier: Programming Language :: Python :: 3
Classifier: License :: OSI Approved :: MIT License
Classifier: Operating System :: OS Independent
Requires-Python: >=3.5
